ijepa/__init__.py
ijepa/helper.py
ijepa/main.py
ijepa/main_distributed.py
ijepa/train.py
ijepa/transforms.py
ijepa/datasets/__init__.py
ijepa/datasets/cagdataset.py
ijepa/datasets/imagenet1k.py
ijepa/masks/__init__.py
ijepa/masks/default.py
ijepa/masks/multiblock.py
ijepa/masks/random.py
ijepa/masks/utils.py
ijepa/models/__init__.py
ijepa/models/vision_transformer.py
ijepa/utils/__init__.py
ijepa/utils/distributed.py
ijepa/utils/logging.py
ijepa/utils/schedulers.py
ijepa/utils/tensors.py
cag_ijepa-0.0.1.dist-info/LICENSE
cag_ijepa-0.0.1.dist-info/METADATA
cag_ijepa-0.0.1.dist-info/WHEEL
cag_ijepa-0.0.1.dist-info/top_level.txt
cag_ijepa-0.0.1.dist-info/RECORD
